README.md
setup.cfg
setup.py
Liacord/__init__.py
Liacord/client.py
Liacord/context.py
Liacord/embed.py
Liacord/intents.py
Liacord.egg-info/PKG-INFO
Liacord.egg-info/SOURCES.txt
Liacord.egg-info/dependency_links.txt
Liacord.egg-info/not-zip-safe
Liacord.egg-info/requires.txt
Liacord.egg-info/top_level.txt