Metadata-Version: 2.1
Name: Liacord
Version: 0.1.9
Summary: A Python wrapper for the Discord API
Home-page: https://github.com/masezev/Liacord.py
Author: Masezev
Author-email: csgomanagement1@gmail.com
License: MIT
Project-URL: Discord, https://discord.gg/H7FQFGEPz5
Keywords: A Python wrapper for the Discord API
Requires-Python: >=3.8.0
